plagiarismdetector
tests
