Metadata-Version: 1.0
Name: PlagiarismDetector
Version: 0.2.1
Summary: Calculates percentage of N-Tuples from file1 found in another file2
Home-page: http://pypi.python.org/pypi/PlagiarismDetector/
Author: Ayush Singh
Author-email: singhay@ccs.neu.edu
License: MIT
Platform: UNKNOWN
